inmemory/__init__.py
inmemory/cli.py
inmemory/client.py
inmemory/memory.py
inmemory/api/__init__.py
inmemory/api/deploy.py
inmemory/api/server.py
inmemory/common/__init__.py
inmemory/common/constants.py
inmemory/common/duplicate_detector.py
inmemory/common/temporal_utils.py
inmemory/config/__init__.py
inmemory/config/config.py
inmemory/embeddings/__init__.py
inmemory/embeddings/base.py
inmemory/embeddings/ollama.py
inmemory/embeddings/openai.py
inmemory/repositories/__init__.py
inmemory/repositories/mongodb_user_manager.py
inmemory/repositories/qdrant_db.py
inmemory/search/__init__.py
inmemory/search/enhanced_search_engine.py
inmemory/security/__init__.py
inmemory/security/encryption.py
inmemory/services/__init__.py
inmemory/services/add_memory.py
inmemory/services/retrieve_memory.py
inmemory/stores/__init__.py
inmemory/stores/base.py
inmemory/stores/mongodb_store.py
inmemory/utils/__init__.py
inmemory/utils/embeddings.py
inmemory/vector_stores/__init__.py
inmemory/vector_stores/base.py
inmemory/vector_stores/chroma.py
inmemory/vector_stores/qdrant.py
inmemory-0.1.11.dist-info/licenses/LICENSE.txt
inmemory-0.1.11.dist-info/METADATA
inmemory-0.1.11.dist-info/WHEEL
inmemory-0.1.11.dist-info/entry_points.txt
inmemory-0.1.11.dist-info/top_level.txt
inmemory-0.1.11.dist-info/RECORD
