Metadata-Version: 2.4
Name: inmemory
Version: 0.1.11
Summary: Enhanced Memory Management for AI Agents with zero-setup simplicity
Author-email: InMemory Team <shrijayan@cpluz.com>
Maintainer-email: InMemory Team <shrijayan@cpluz.com>
License-Expression: Apache-2.0
Project-URL: Homepage, https://github.com/shrijayan/inmemory
Project-URL: Repository, https://github.com/shrijayan/inmemory
Project-URL: Documentation, https://github.com/shrijayan/inmemory#readme
Project-URL: Issues, https://github.com/shrijayan/inmemory/issues
Project-URL: Changelog, https://github.com/shrijayan/inmemory/blob/main/CHANGELOG.md
Keywords: memory,ai,ml,vector,search,embeddings,agents,llm,artificial-intelligence,qdrant,semantic-search
Classifier: Development Status :: 4 - Beta
Classifier: Intended Audience :: Developers
Classifier: Operating System :: OS Independent
Classifier: Programming Language :: Python :: 3
Classifier: Programming Language :: Python :: 3.10
Classifier: Programming Language :: Python :: 3.11
Classifier: Programming Language :: Python :: 3.12
Classifier: Programming Language :: Python :: 3.13
Classifier: Topic :: Scientific/Engineering :: Artificial Intelligence
Classifier: Topic :: Software Development :: Libraries :: Python Modules
Classifier: Topic :: Database :: Database Engines/Servers
Classifier: Topic :: Text Processing :: Indexing
Classifier: Typing :: Typed
Requires-Python: >=3.10
License-File: LICENSE.txt
Requires-Dist: chromadb>=0.4.0
Requires-Dist: qdrant-client>=1.6.0
Requires-Dist: pydantic<3.0.0,>=2.0.0
Requires-Dist: python-dotenv>=1.0.0
Requires-Dist: cryptography>=40.0.0
Requires-Dist: httpx>=0.25.0
Requires-Dist: fastapi>=0.100.0
Requires-Dist: uvicorn>=0.20.0
Requires-Dist: starlette>=0.27.0
Requires-Dist: ollama>=0.1.0
Requires-Dist: openai>=1.0.0
Requires-Dist: pyyaml>=6.0.0
Provides-Extra: enterprise
Requires-Dist: pymongo>=4.0.0; extra == "enterprise"
Requires-Dist: authlib>=1.2.0; extra == "enterprise"
Requires-Dist: google-auth>=2.15.0; extra == "enterprise"
Requires-Dist: mcp[cli]>=1.0.0; python_version >= "3.10" and extra == "enterprise"
Requires-Dist: fastmcp>=2.0.0; python_version >= "3.10" and extra == "enterprise"
Provides-Extra: dev
Requires-Dist: ruff>=0.2.0; extra == "dev"
Requires-Dist: pre-commit>=3.0.0; extra == "dev"
Requires-Dist: pytest>=7.0.0; extra == "dev"
Requires-Dist: pytest-asyncio>=0.21.0; extra == "dev"
Provides-Extra: test
Requires-Dist: pytest>=7.0.0; extra == "test"
Requires-Dist: pytest-asyncio>=0.21.0; extra == "test"
Requires-Dist: pytest-mock>=3.10.0; extra == "test"
Dynamic: license-file
